rpl/__init__.py
rpl/__main__.py
rpl-1.18.data/data/share/man/man1/rpl.1
rpl-1.18.dist-info/COPYING
rpl-1.18.dist-info/METADATA
rpl-1.18.dist-info/WHEEL
rpl-1.18.dist-info/entry_points.txt
rpl-1.18.dist-info/top_level.txt
rpl-1.18.dist-info/RECORD
