Metadata-Version: 2.2
Name: rpl
Version: 1.18
Summary: Replace strings in files
Author-email: Reuben Thomas <rrt@sc3d.org>
License: GPL v3 or later
Project-URL: Homepage, https://github.com/rrthomas/rpl
Project-URL: Source, https://github.com/rrthomas/rpl
Classifier: Environment :: Console
Classifier: Programming Language :: Python :: 3
Requires-Python: >=3.9
License-File: COPYING
Requires-Dist: regex>=2022.3.2
Requires-Dist: chardet
Requires-Dist: chainstream
